bdist_docker-0.1.1.dist-info/WHEEL
bdist_docker-0.1.1.dist-info/DESCRIPTION.rst
bdist_docker-0.1.1.dist-info/entry_points.txt
bdist_docker-0.1.1.dist-info/metadata.json
bdist_docker-0.1.1.dist-info/RECORD
bdist_docker-0.1.1.dist-info/top_level.txt
bdist_docker-0.1.1.dist-info/METADATA
bdist_docker/__init__.py
