Metadata-Version: 2.0
Name: bdist-docker
Version: 0.1.1
Summary: Distutils extension command to build docker images for python applications.
Home-page: https://github.com/zalando/bdist_docker/
Author: Zalando SE
Author-email: UNKNOWN
License: Apache License Version 2.0
Platform: UNKNOWN
Classifier: Development Status :: 4 - Beta
Classifier: Intended Audience :: Developers
Classifier: Programming Language :: Python
Classifier: Programming Language :: Python :: 2.7
Classifier: Programming Language :: Python :: 3
Classifier: Programming Language :: Python :: 3.4
Requires-Dist: wheel
